<?xml version="1.0" encoding="utf-8"?>
<!DOCTYPE hibernate-mapping PUBLIC "-//Hibernate/Hibernate Mapping DTD 3.0//EN"
"http://hibernate.sourceforge.net/hibernate-mapping-3.0.dtd">
<!-- 
    Mapping file autogenerated by MyEclipse Persistence Tools
-->
<hibernate-mapping>
    <class name="com.weili.wechat.hibernate.SysRole" table="SYS_ROLE" >
        <id name="no" type="integer">
            <column name="NO" precision="22" scale="0" />
            <generator class="assigned" />
        </id>
        <property name="name" type="string">
            <column name="NAME" length="50" not-null="true" />
        </property>
        <property name="catalog" type="integer">
            <column name="CATALOG" precision="22" scale="0" not-null="true" />
        </property>
        <property name="orgType" type="integer">
            <column name="ORG_TYPE" precision="22" scale="0" />
        </property>
        <property name="note" type="string">
            <column name="NOTE" length="200" />
        </property>
        <set name="sysConfRoleMenus" inverse="true">
            <key>
                <column name="ROLENO" precision="22" scale="0" not-null="true" />
            </key>
            <one-to-many class="com.weili.wechat.hibernate.SysConfRoleMenu" />
        </set>
        <set name="sysConfRoleButtons" inverse="true">
            <key>
                <column name="ROLENO" precision="22" scale="0" not-null="true" />
            </key>
            <one-to-many class="com.weili.wechat.hibernate.SysConfRoleButton" />
        </set>
        <set name="opTables" inverse="true">
            <key>
                <column name="ROLE" precision="22" scale="0" not-null="true" />
            </key>
            <one-to-many class="com.weili.wechat.hibernate.OpTable" />
        </set>
    </class>
</hibernate-mapping>
